odoo/addons/delivery_translatable/README.rst
odoo/addons/delivery_translatable/__init__.py
odoo/addons/delivery_translatable/__manifest__.py
odoo/addons/delivery_translatable/i18n/delivery_translatable.pot
odoo/addons/delivery_translatable/i18n/es.po
odoo/addons/delivery_translatable/models/__init__.py
odoo/addons/delivery_translatable/models/delivery.py
odoo/addons/delivery_translatable/readme/CONTRIBUTORS.rst
odoo/addons/delivery_translatable/readme/DESCRIPTION.rst
odoo/addons/delivery_translatable/static/description/icon.png
odoo/addons/delivery_translatable/static/description/index.html
odoo_addon_delivery_translatable-15.0.1.0.0.6.dist-info/METADATA
odoo_addon_delivery_translatable-15.0.1.0.0.6.dist-info/WHEEL
odoo_addon_delivery_translatable-15.0.1.0.0.6.dist-info/top_level.txt
odoo_addon_delivery_translatable-15.0.1.0.0.6.dist-info/RECORD
